{
  "routes": [
    {
      "method": "GET",
      "path": "/users-histories",
      "handler": "users-history.find",
      "config": {
        "policies": []
      }
    },
    {
      "method": "GET",
      "path": "/users-histories/count",
      "handler": "users-history.count",
      "config": {
        "policies": []
      }
    },
    {
      "method": "GET",
      "path": "/users-histories/:id",
      "handler": "users-history.findOne",
      "config": {
        "policies": []
      }
    },
    {
      "method": "POST",
      "path": "/users-histories",
      "handler": "users-history.create",
      "config": {
        "policies": []
      }
    },
    {
      "method": "PUT",
      "path": "/users-histories/:id",
      "handler": "users-history.update",
      "config": {
        "policies": []
      }
    },
    {
      "method": "DELETE",
      "path": "/users-histories/:id",
      "handler": "users-history.delete",
      "config": {
        "policies": []
      }
    }
  ]
}
